setup.py
dvaa/__init__.py
dvaa/base.py
dvaa/compat.py
dvaa/validators.py
dvaa.egg-info/PKG-INFO
dvaa.egg-info/SOURCES.txt
dvaa.egg-info/dependency_links.txt
dvaa.egg-info/requires.txt
dvaa.egg-info/top_level.txt