Metadata-Version: 2.1
Name: dvaa
Version: 0.4.2
Summary: Lightweight data validation and adaptation library for Python
Author: Rayan Haddad
Author-email: rayan.m.haddad@proton.me
Keywords: validation adaptation typechecking jsonschema
Classifier: Development Status :: 5 - Production/Stable
Classifier: Intended Audience :: Developers
Classifier: Operating System :: OS Independent
Classifier: Programming Language :: Python :: 2
Classifier: Programming Language :: Python :: 2.7
Classifier: Programming Language :: Python :: 3
Classifier: Programming Language :: Python :: 3.3
Classifier: Programming Language :: Python :: 3.4
Classifier: Topic :: Software Development :: Libraries :: Python Modules
Classifier: License :: OSI Approved :: MIT License
Requires-Dist: decorator
